json_schema_matchers/__init__.py
json_schema_matchers/common_matcher.py
tests/__init__.py
json_schema_matchers-0.1.3.dist-info/LICENSE
json_schema_matchers-0.1.3.dist-info/METADATA
json_schema_matchers-0.1.3.dist-info/WHEEL
json_schema_matchers-0.1.3.dist-info/top_level.txt
json_schema_matchers-0.1.3.dist-info/RECORD
