Metadata-Version: 2.1
Name: json-schema-matchers
Version: 0.1.3
Summary: PyHamcrest matchers extension for json schema validation
Home-page: https://github.com/JamalZeynalov/json-schema-matchers
Author: Jamal Zeinalov
Author-email: jamal.zeynalov@gmail.com
Classifier: Programming Language :: Python :: 3
Classifier: License :: OSI Approved :: MIT License
Classifier: Operating System :: OS Independent
Requires-Python: >=3.6
License-File: LICENSE
Requires-Dist: jsonschema (>=3.2.0)
Requires-Dist: PyHamcrest (>=2.0.2)
